Metadata-Version: 1.0
Name: rmcolors
Version: 0.0.1b0
Summary: Imprime texto a color en la consola
Home-page: https://github.com/raudin17/rmcolors
Author: Raudin Moreno
Author-email: raudin247@gmail.com
License: Copyright 2018 rcolor
